setup.py
pyimap4utf7/__init__.py
pyimap4utf7/imap4utf7.py
pyimap4utf7.egg-info/PKG-INFO
pyimap4utf7.egg-info/SOURCES.txt
pyimap4utf7.egg-info/dependency_links.txt
pyimap4utf7.egg-info/not-zip-safe
pyimap4utf7.egg-info/top_level.txt