Metadata-Version: 1.0
Name: pyimap4utf7
Version: 0.0.1
Summary: IMAP4 style UTF7 encoder/decoder in python
Home-page: https://github.com/DanielBlack/pyimap4utf7
Author: danielblack
Author-email: danielblack@danielblack.name
License: MIT
Keywords: imap4 utf7
Platform: UNKNOWN
